<?xml version="1.0" encoding="utf-8"?>
<odoo>

    <record id="partner_form" model="ir.ui.view">
        <field name="name">fiscal.partner.form</field>
        <field name="model">res.partner</field>
        <field name="inherit_id" ref="l10n_br_base.l10n_br_base_partner_form"/>
        <field name="arch" type="xml">
            <group name="fiscal" position="inside">
                <group string="Fiscal Profile" name="fiscal_profile">
                    <field name="fiscal_profile_id" widget="radio" required="1"/>
                    <field name="ind_ie_dest" attrs="{'readonly': [('fiscal_profile_id', '!=', False)]}"/>
                    <field name="tax_framework" attrs="{'readonly': [('fiscal_profile_id', '!=', False)]}"/>
                    <field name="cnae_main_id"/>
                </group>
            </group>
            <field name="state_tax_number_ids" position="attributes">
                <attribute name="attrs">{'invisible': [('ind_ie_dest','=', '9')]}</attribute>
            </field>
            <field name="inscr_est" position="attributes">
                <attribute name="attrs">{'invisible': [('ind_ie_dest','=', '9')]}</attribute>
            </field>
            <label name="inscr_est" position="attributes">
                <attribute name="attrs">{'invisible': [('is_company','!=', True), ('ind_ie_dest','=', '9')]}</attribute>
            </label>
        </field>
    </record>

</odoo>
